<annotation>
	<folder></folder>
	<filename>143_jpg.rf.b3a443a2aeeead045949481deebaafbd.jpg</filename>
	<path>143_jpg.rf.b3a443a2aeeead045949481deebaafbd.jpg</path>
	<source>
		<database>roboflow.com</database>
	</source>
	<size>
		<width>640</width>
		<height>640</height>
		<depth>3</depth>
	</size>
	<segmented>0</segmented>
	<object>
		<name>id</name>
		<pose>Unspecified</pose>
		<truncated>0</truncated>
		<difficult>0</difficult>
		<occluded>0</occluded>
		<bndbox>
			<xmin>51</xmin>
			<xmax>578</xmax>
			<ymin>102</ymin>
			<ymax>553</ymax>
		</bndbox>
		<polygon>
			<x1>50.357924</x1>
			<y1>196.482878</y1>
			<x2>59.896759</x2>
			<y2>276.68513</y2>
			<x3>138.652721</x3>
			<y3>542.204277</y3>
			<x4>154.803117</x4>
			<y4>552.282345</y4>
			<x5>575.611928</x5>
			<y5>492.371998</y5>
			<x6>577.377931</x6>
			<y6>403.640016</y6>
			<x7>553.807902</x7>
			<y7>206.881316</y7>
			<x8>564.014399</x8>
			<y8>179.431085</y8>
			<x9>563.124984</x9>
			<y9>173.815537</y9>
			<x10>543.127341</x10>
			<y10>107.484636</y10>
			<x11>529.468773</x11>
			<y11>100.529822</y11>
			<x12>505.516076</x12>
			<y12>104.323557</y12>
			<x13>50.357924</x13>
			<y13>196.482878</y13>
		</polygon>
	</object>
</annotation>
