<annotation>
	<folder></folder>
	<filename>320_jpg.rf.51ad0225c61bf75d44d77ba1cef6bd24.jpg</filename>
	<path>320_jpg.rf.51ad0225c61bf75d44d77ba1cef6bd24.jpg</path>
	<source>
		<database>roboflow.com</database>
	</source>
	<size>
		<width>640</width>
		<height>640</height>
		<depth>3</depth>
	</size>
	<segmented>0</segmented>
	<object>
		<name>id</name>
		<pose>Unspecified</pose>
		<truncated>0</truncated>
		<difficult>0</difficult>
		<occluded>0</occluded>
		<bndbox>
			<xmin>149</xmin>
			<xmax>623</xmax>
			<ymin>1</ymin>
			<ymax>589</ymax>
		</bndbox>
		<polygon>
			<x1>361.686337</x1>
			<y1>0</y1>
			<x2>184.590043</x2>
			<y2>91.867688</y2>
			<x3>147.591081</x3>
			<y3>111.540385</y3>
			<x4>393.272423</x4>
			<y4>588.232292</y4>
			<x5>621.387752</x5>
			<y5>475.422223</y5>
			<x6>622.480946</x6>
			<y6>456.482864</y6>
			<x7>596.150452</x7>
			<y7>406.962407</y7>
			<x8>366.541005</x8>
			<y8>0</y8>
			<x9>361.686337</x9>
			<y9>0</y9>
		</polygon>
	</object>
</annotation>
