<annotation>
	<folder></folder>
	<filename>380_jpg.rf.1423190055f5b45e566e499f6708632b.jpg</filename>
	<path>380_jpg.rf.1423190055f5b45e566e499f6708632b.jpg</path>
	<source>
		<database>roboflow.com</database>
	</source>
	<size>
		<width>640</width>
		<height>640</height>
		<depth>3</depth>
	</size>
	<segmented>0</segmented>
	<object>
		<name>id</name>
		<pose>Unspecified</pose>
		<truncated>0</truncated>
		<difficult>0</difficult>
		<occluded>0</occluded>
		<bndbox>
			<xmin>207</xmin>
			<xmax>560</xmax>
			<ymin>1</ymin>
			<ymax>572</ymax>
		</bndbox>
		<polygon>
			<x1>309.383461</x1>
			<y1>0</y1>
			<x2>215.58099</x2>
			<y2>50.041804</y2>
			<x3>205.639807</x3>
			<y3>70.483772</y3>
			<x4>401.013716</x4>
			<y4>544.040663</y4>
			<x5>418.157856</x5>
			<y5>571.458146</y5>
			<x6>559.492545</x6>
			<y6>515.84845</y6>
			<x7>402.453163</x7>
			<y7>115.650263</y7>
			<x8>355.727424</x8>
			<y8>0</y8>
			<x9>309.383461</x9>
			<y9>0</y9>
		</polygon>
	</object>
</annotation>
