<annotation>
	<folder></folder>
	<filename>382_jpg.rf.b359fd1e97f44a9bb3aed6c3193858a6.jpg</filename>
	<path>382_jpg.rf.b359fd1e97f44a9bb3aed6c3193858a6.jpg</path>
	<source>
		<database>roboflow.com</database>
	</source>
	<size>
		<width>640</width>
		<height>640</height>
		<depth>3</depth>
	</size>
	<segmented>0</segmented>
	<object>
		<name>id</name>
		<pose>Unspecified</pose>
		<truncated>0</truncated>
		<difficult>0</difficult>
		<occluded>0</occluded>
		<bndbox>
			<xmin>42</xmin>
			<xmax>603</xmax>
			<ymin>70</ymin>
			<ymax>505</ymax>
		</bndbox>
		<polygon>
			<x1>590.786253</x1>
			<y1>467.398831</y1>
			<x2>602.421601</x2>
			<y2>81.989589</y2>
			<x3>536.834991</x3>
			<y3>68.899344</y3>
			<x4>133.006558</x4>
			<y4>74.929847</y4>
			<x5>44.662827</x5>
			<y5>385.341487</y5>
			<x6>40.927637</x6>
			<y6>438.987183</y6>
			<x7>64.528143</x7>
			<y7>454.211058</y7>
			<x8>573.485636</x8>
			<y8>503.700578</y8>
			<x9>590.786253</x9>
			<y9>467.398831</y9>
		</polygon>
	</object>
</annotation>
