<annotation>
	<folder></folder>
	<filename>412_jpg.rf.30d060bb7eb5ad63d11c3529b9127b58.jpg</filename>
	<path>412_jpg.rf.30d060bb7eb5ad63d11c3529b9127b58.jpg</path>
	<source>
		<database>roboflow.com</database>
	</source>
	<size>
		<width>640</width>
		<height>640</height>
		<depth>3</depth>
	</size>
	<segmented>0</segmented>
	<object>
		<name>id</name>
		<pose>Unspecified</pose>
		<truncated>0</truncated>
		<difficult>0</difficult>
		<occluded>0</occluded>
		<bndbox>
			<xmin>95</xmin>
			<xmax>487</xmax>
			<ymin>17</ymin>
			<ymax>621</ymax>
		</bndbox>
		<polygon>
			<x1>485.578591</x1>
			<y1>540.330677</y1>
			<x2>336.679119</x2>
			<y2>16.022871</y2>
			<x3>94.46328</x3>
			<y3>85.231322</y3>
			<x4>227.066434</x4>
			<y4>601.846361</y4>
			<x5>244.739491</x5>
			<y5>619.506815</y5>
			<x6>485.578591</x6>
			<y6>540.330677</y6>
		</polygon>
	</object>
</annotation>
