<annotation>
	<folder></folder>
	<filename>414_jpg.rf.bf6b95d59b38956124bde74052b0f37e.jpg</filename>
	<path>414_jpg.rf.bf6b95d59b38956124bde74052b0f37e.jpg</path>
	<source>
		<database>roboflow.com</database>
	</source>
	<size>
		<width>640</width>
		<height>640</height>
		<depth>3</depth>
	</size>
	<segmented>0</segmented>
	<object>
		<name>id</name>
		<pose>Unspecified</pose>
		<truncated>0</truncated>
		<difficult>0</difficult>
		<occluded>0</occluded>
		<bndbox>
			<xmin>1</xmin>
			<xmax>597</xmax>
			<ymin>28</ymin>
			<ymax>641</ymax>
		</bndbox>
		<polygon>
			<x1>204.114527</x1>
			<y1>640</y1>
			<x2>587.031804</x2>
			<y2>438.621525</y2>
			<x3>595.949269</x3>
			<y3>415.783928</y3>
			<x4>444.2756</x4>
			<y4>26.80296</y4>
			<x5>0</x5>
			<y5>139.374314</y5>
			<x6>0</x6>
			<y6>262.678621</y6>
			<x7>153.60398</x7>
			<y7>640</y7>
			<x8>204.114527</x8>
			<y8>640</y8>
		</polygon>
	</object>
</annotation>
