<annotation>
	<folder></folder>
	<filename>484_jpg.rf.5d522c7271eb42769f1e8af30d37dca9.jpg</filename>
	<path>484_jpg.rf.5d522c7271eb42769f1e8af30d37dca9.jpg</path>
	<source>
		<database>roboflow.com</database>
	</source>
	<size>
		<width>640</width>
		<height>640</height>
		<depth>3</depth>
	</size>
	<segmented>0</segmented>
	<object>
		<name>id</name>
		<pose>Unspecified</pose>
		<truncated>0</truncated>
		<difficult>0</difficult>
		<occluded>0</occluded>
		<bndbox>
			<xmin>111</xmin>
			<xmax>417</xmax>
			<ymin>180</ymin>
			<ymax>516</ymax>
		</bndbox>
		<polygon>
			<x1>416.074515</x1>
			<y1>455.219775</y1>
			<x2>416.425223</x2>
			<y2>426.500197</y2>
			<x3>357.050042</x3>
			<y3>182.088994</y3>
			<x4>336.953106</x4>
			<y4>178.991766</y4>
			<x5>121.094048</x5>
			<y5>219.67712</y5>
			<x6>110.393204</x6>
			<y6>230.034226</y6>
			<x7>114.429851</x7>
			<y7>246.440426</y7>
			<x8>187.917215</x8>
			<y8>515.486511</y8>
			<x9>416.074515</x9>
			<y9>455.219775</y9>
		</polygon>
	</object>
</annotation>
