<annotation>
	<folder></folder>
	<filename>48_jpg.rf.20543822a1ab14b9c0b58f7a9dcc4fdc.jpg</filename>
	<path>48_jpg.rf.20543822a1ab14b9c0b58f7a9dcc4fdc.jpg</path>
	<source>
		<database>roboflow.com</database>
	</source>
	<size>
		<width>640</width>
		<height>640</height>
		<depth>3</depth>
	</size>
	<segmented>0</segmented>
	<object>
		<name>id</name>
		<pose>Unspecified</pose>
		<truncated>0</truncated>
		<difficult>0</difficult>
		<occluded>0</occluded>
		<bndbox>
			<xmin>45</xmin>
			<xmax>543</xmax>
			<ymin>22</ymin>
			<ymax>618</ymax>
		</bndbox>
		<polygon>
			<x1>518.677632</x1>
			<y1>616.175</y1>
			<x2>535.552632</x2>
			<y2>607.8625</y2>
			<x3>542.427632</x3>
			<y3>580.55</y3>
			<x4>542.427632</x4>
			<y4>58.05</y4>
			<x5>534.302632</x5>
			<y5>30.7375</y5>
			<x6>64.302632</x6>
			<y6>21.2375</y6>
			<x7>47.427632</x7>
			<y7>34.3</y7>
			<x8>43.677632</x8>
			<y8>575.8</y8>
			<x9>50.552632</x9>
			<y9>607.8625</y9>
			<x10>86.802632</x10>
			<y10>617.3625</y10>
			<x11>518.677632</x11>
			<y11>616.175</y11>
		</polygon>
	</object>
</annotation>
