<annotation>
	<folder></folder>
	<filename>585_jpg.rf.f1bd9b5ceeb4c34233d7bd48306e1ddb.jpg</filename>
	<path>585_jpg.rf.f1bd9b5ceeb4c34233d7bd48306e1ddb.jpg</path>
	<source>
		<database>roboflow.com</database>
	</source>
	<size>
		<width>640</width>
		<height>640</height>
		<depth>3</depth>
	</size>
	<segmented>0</segmented>
	<object>
		<name>id</name>
		<pose>Unspecified</pose>
		<truncated>0</truncated>
		<difficult>0</difficult>
		<occluded>0</occluded>
		<bndbox>
			<xmin>183</xmin>
			<xmax>603</xmax>
			<ymin>2</ymin>
			<ymax>589</ymax>
		</bndbox>
		<polygon>
			<x1>181.941271</x1>
			<y1>67.273804</y1>
			<x2>379.605832</x2>
			<y2>492.382729</y2>
			<x3>431.111431</x3>
			<y3>587.961436</y3>
			<x4>601.678553</x4>
			<y4>497.323897</y4>
			<x5>363.462737</x5>
			<y5>0.888737</y5>
			<x6>196.798418</x6>
			<y6>51.002129</y6>
			<x7>181.941271</x7>
			<y7>67.273804</y7>
		</polygon>
	</object>
</annotation>
