<annotation>
	<folder></folder>
	<filename>817_jpg.rf.c237339e47c25f4620cb8e5424b43b4a.jpg</filename>
	<path>817_jpg.rf.c237339e47c25f4620cb8e5424b43b4a.jpg</path>
	<source>
		<database>roboflow.com</database>
	</source>
	<size>
		<width>640</width>
		<height>640</height>
		<depth>3</depth>
	</size>
	<segmented>0</segmented>
	<object>
		<name>id</name>
		<pose>Unspecified</pose>
		<truncated>0</truncated>
		<difficult>0</difficult>
		<occluded>0</occluded>
		<bndbox>
			<xmin>44</xmin>
			<xmax>607</xmax>
			<ymin>205</ymin>
			<ymax>367</ymax>
		</bndbox>
		<polygon>
			<x1>590.632812</x1>
			<y1>206.25</y1>
			<x2>208.140625</x2>
			<y2>204.375</y2>
			<x3>60.820312</x3>
			<y3>203.75</y3>
			<x4>43.25</x4>
			<y4>210.625</y4>
			<x5>47.304688</x5>
			<y5>365</y5>
			<x6>585.226562</x6>
			<y6>366.25</y6>
			<x7>605.5</x7>
			<y7>360.625</y7>
			<x8>590.632812</x8>
			<y8>206.25</y8>
		</polygon>
	</object>
</annotation>
