<annotation>
	<folder></folder>
	<filename>817_jpg.rf.40b1dd320355137b67342af2203ada61.jpg</filename>
	<path>817_jpg.rf.40b1dd320355137b67342af2203ada61.jpg</path>
	<source>
		<database>roboflow.com</database>
	</source>
	<size>
		<width>640</width>
		<height>640</height>
		<depth>3</depth>
	</size>
	<segmented>0</segmented>
	<object>
		<name>id</name>
		<pose>Unspecified</pose>
		<truncated>0</truncated>
		<difficult>0</difficult>
		<occluded>0</occluded>
		<bndbox>
			<xmin>131</xmin>
			<xmax>572</xmax>
			<ymin>56</ymin>
			<ymax>603</ymax>
		</bndbox>
		<polygon>
			<x1>129.718312</x1>
			<y1>509.637456</y1>
			<x2>253.849236</x2>
			<y2>601.504724</y2>
			<x3>269.558823</x3>
			<y3>591.055304</y3>
			<x4>353.546312</x4>
			<y4>470.019084</y4>
			<x5>571.398908</x5>
			<y5>155.624371</y5>
			<x6>453.469779</x6>
			<y6>54.900022</y6>
			<x7>437.233683</x7>
			<y7>68.280682</y7>
			<x8>129.718312</x8>
			<y8>509.637456</y8>
		</polygon>
	</object>
</annotation>
