<annotation>
	<folder></folder>
	<filename>IMG-20231114-WA0025_jpg.rf.6a76733477dad6ab864c338b0f4884ca.jpg</filename>
	<path>IMG-20231114-WA0025_jpg.rf.6a76733477dad6ab864c338b0f4884ca.jpg</path>
	<source>
		<database>roboflow.com</database>
	</source>
	<size>
		<width>640</width>
		<height>640</height>
		<depth>3</depth>
	</size>
	<segmented>0</segmented>
	<object>
		<name>id</name>
		<pose>Unspecified</pose>
		<truncated>0</truncated>
		<difficult>0</difficult>
		<occluded>0</occluded>
		<bndbox>
			<xmin>178</xmin>
			<xmax>325</xmax>
			<ymin>143</ymin>
			<ymax>409</ymax>
		</bndbox>
		<polygon>
			<x1>312.20893</x1>
			<y1>240.4126</y1>
			<x2>313.246496</x2>
			<y2>238.60602</y2>
			<x3>310.80911</x3>
			<y3>218.755097</y3>
			<x4>311.846677</x4>
			<y4>216.948516</y4>
			<x5>309.40929</x5>
			<y5>197.097593</y5>
			<x6>310.446858</x6>
			<y6>195.291014</y6>
			<x7>307.603239</x7>
			<y7>172.131602</y7>
			<x8>308.640806</x8>
			<y8>170.325023</y8>
			<x9>306.812767</x9>
			<y9>155.436831</y9>
			<x10>303.000155</x10>
			<y10>150.027819</y10>
			<x11>295.149828</x11>
			<y11>147.633352</y11>
			<x12>258.560683</x12>
			<y12>147.088386</y12>
			<x13>248.22899</x13>
			<y13>144.998592</y13>
			<x14>230.859433</x14>
			<y14>147.131306</y14>
			<x15>226.731153</x15>
			<y15>144.279827</y15>
			<x16>211.639845</x16>
			<y16>144.453625</y16>
			<x17>202.548835</x17>
			<y17>142.211494</y17>
			<x18>192.623374</x18>
			<y18>143.430188</y18>
			<x19>191.179576</x19>
			<y19>141.928281</y19>
			<x20>183.735479</x20>
			<y20>142.842301</y20>
			<x21>180.103995</x21>
			<y21>149.165332</y21>
			<x22>178.775355</x22>
			<y22>189.628862</y22>
			<x23>179.840124</x23>
			<y23>270.09891</y23>
			<x24>178.127242</x24>
			<y24>297.176155</y24>
			<x25>179.345936</x25>
			<y25>307.101616</y25>
			<x26>178.061274</x26>
			<y26>327.409549</y26>
			<x27>179.279968</x27>
			<y27>337.335011</y27>
			<x28>177.770202</x28>
			<y28>366.066498</y28>
			<x29>178.76379</x29>
			<y29>384.415513</y29>
			<x30>177.298003</x30>
			<y30>392.991405</y30>
			<x31>178.832365</x31>
			<y31>400.359333</y31>
			<x32>181.923077</x32>
			<y32>405.017391</y32>
			<x33>187.292038</x33>
			<y33>407.716531</y33>
			<x34>195.976817</x34>
			<y34>406.650174</y34>
			<x35>197.420616</x35>
			<y35>408.152081</y35>
			<x36>255.101366</x36>
			<y36>406.107325</y36>
			<x37>256.545164</x37>
			<y37>407.609232</y37>
			<x38>268.951991</x38>
			<y38>406.085865</y38>
			<x39>270.39579</x39>
			<y39>407.587771</y39>
			<x40>294.171876</x40>
			<y40>406.347618</y40>
			<x41>295.615674</x41>
			<y41>407.849525</y41>
			<x42>306.781818</x42>
			<y42>406.478494</y42>
			<x43>308.225617</x43>
			<y43>407.980402</y43>
			<x44>319.391761</x44>
			<y44>406.609372</y44>
			<x45>323.226362</x45>
			<y45>401.940584</y45>
			<x46>324.285918</x46>
			<y46>390.056206</y46>
			<x47>315.211685</x47>
			<y47>285.381851</y47>
			<x48>316.249251</x48>
			<y48>283.57527</y48>
			<x49>312.20893</x49>
			<y49>240.4126</y49>
		</polygon>
	</object>
</annotation>
