<annotation>
	<folder></folder>
	<filename>IMG-20231114-WA0039_jpg.rf.c91aa4d2e3a4c051c30a75497a6d6fcc.jpg</filename>
	<path>IMG-20231114-WA0039_jpg.rf.c91aa4d2e3a4c051c30a75497a6d6fcc.jpg</path>
	<source>
		<database>roboflow.com</database>
	</source>
	<size>
		<width>640</width>
		<height>640</height>
		<depth>3</depth>
	</size>
	<segmented>0</segmented>
	<object>
		<name>id</name>
		<pose>Unspecified</pose>
		<truncated>0</truncated>
		<difficult>0</difficult>
		<occluded>0</occluded>
		<bndbox>
			<xmin>64</xmin>
			<xmax>544</xmax>
			<ymin>247</ymin>
			<ymax>549</ymax>
		</bndbox>
		<polygon>
			<x1>542.161526</x1>
			<y1>344.396592</y1>
			<x2>535.942716</x2>
			<y2>338.337134</y2>
			<x3>511.987726</x3>
			<y3>331.076217</y3>
			<x4>510.068164</x4>
			<y4>331.885884</y4>
			<x5>399.49651</x5>
			<y5>306.893808</y5>
			<x6>397.576948</x6>
			<y6>307.703474</y6>
			<x7>322.885206</x7>
			<y7>290.368999</y7>
			<x8>320.965645</x8>
			<y8>291.178665</y8>
			<x9>272.450858</x9>
			<y9>279.082571</y9>
			<x10>270.531297</x10>
			<y10>279.892237</y10>
			<x11>120.845411</x11>
			<y11>246.436155</y11>
			<x12>112.154809</x12>
			<y12>246.845879</y12>
			<x13>105.436342</x13>
			<y13>249.679712</y13>
			<x14>103.871756</x14>
			<y14>252.510285</y14>
			<x15>94.444709</x15>
			<y15>286.875468</y15>
			<x16>95.759467</x16>
			<y16>288.491541</y16>
			<x17>81.046898</x17>
			<y17>354.389705</y17>
			<x18>82.361656</x18>
			<y18>356.005778</y18>
			<x19>66.939135</x19>
			<y19>417.862131</y19>
			<x20>68.253892</x20>
			<y20>419.478203</y20>
			<x21>62.508247</x21>
			<y21>442.522728</y21>
			<x22>63.218199</x22>
			<y22>446.56454</y22>
			<x23>67.81985</x23>
			<y23>452.220795</y23>
			<x24>70.751766</x24>
			<y24>454.24007</y24>
			<x25>119.266552</x25>
			<y25>466.336165</y25>
			<x26>121.186114</x26>
			<y26>465.526498</y26>
			<x27>197.495015</x27>
			<y27>483.264178</y27>
			<x28>199.414577</x28>
			<y28>482.454511</y28>
			<x29>256.015161</x29>
			<y29>496.566621</y29>
			<x30>257.934723</x30>
			<y30>495.756955</y30>
			<x31>296.746552</x31>
			<y31>505.433831</y31>
			<x32>298.666113</x32>
			<y32>504.624164</y32>
			<x33>384.677972</x33>
			<y33>524.781063</y33>
			<x34>386.597533</x34>
			<y34>523.971395</y34>
			<x35>409.237767</x35>
			<y35>529.61624</y35>
			<x36>411.157329</x36>
			<y36>528.806573</y36>
			<x37>466.140754</x37>
			<y37>542.51548</y37>
			<x38>468.060316</x38>
			<y38>541.705815</y38>
			<x39>492.317709</x39>
			<y39>547.753862</y39>
			<x40>506.109618</x40>
			<y40>544.107102</y40>
			<x41>512.565216</x41>
			<y41>525.104391</y41>
			<x42>511.250459</x42>
			<y42>523.488318</y42>
			<x43>520.217383</x43>
			<y43>480.634677</y43>
			<x44>518.902625</x44>
			<y44>479.018604</y44>
			<x45>524.043466</x45>
			<y45>458.399819</y45>
			<x46>522.728709</x46>
			<y46>456.783747</y46>
			<x47>525.253074</x47>
			<y47>453.548341</y47>
			<x48>523.938318</x48>
			<y48>451.932268</y48>
			<x49>530.59117</x49>
			<y49>425.249136</y49>
			<x50>529.276412</x50>
			<y50>423.633063</y50>
			<x51>538.243336</x51>
			<y51>380.779422</y51>
			<x52>536.928579</x52>
			<y52>379.16335</y52>
			<x53>542.976626</x53>
			<y53>354.905956</y53>
			<x54>542.161526</x54>
			<y54>344.396592</y54>
		</polygon>
	</object>
</annotation>
