<annotation>
	<folder></folder>
	<filename>IMG-20231114-WA0068_jpg.rf.0fc887be751931ff02351d9587d4138d.jpg</filename>
	<path>IMG-20231114-WA0068_jpg.rf.0fc887be751931ff02351d9587d4138d.jpg</path>
	<source>
		<database>roboflow.com</database>
	</source>
	<size>
		<width>640</width>
		<height>640</height>
		<depth>3</depth>
	</size>
	<segmented>0</segmented>
	<object>
		<name>id</name>
		<pose>Unspecified</pose>
		<truncated>0</truncated>
		<difficult>0</difficult>
		<occluded>0</occluded>
		<bndbox>
			<xmin>294</xmin>
			<xmax>384</xmax>
			<ymin>258</ymin>
			<ymax>358</ymax>
		</bndbox>
		<polygon>
			<x1>335.287835</x1>
			<y1>259.051375</y1>
			<x2>332.461377</x2>
			<y2>256.886946</y2>
			<x3>325.040956</x3>
			<y3>261.52374</y3>
			<x4>323.097697</x4>
			<y4>260.772726</y4>
			<x5>297.656254</x5>
			<y5>276.670303</y5>
			<x6>295.712996</x6>
			<y6>275.919288</y6>
			<x7>293.150722</x7>
			<y7>282.433619</y7>
			<x8>316.820227</x8>
			<y8>322.671596</y8>
			<x9>316.643366</x9>
			<y9>324.747408</y9>
			<x10>328.12495</x10>
			<y10>343.121784</y10>
			<x11>327.948089</x11>
			<y11>345.197596</y11>
			<x12>335.985308</x12>
			<y12>356.880411</y12>
			<x13>338.459152</x13>
			<y13>351.403988</y13>
			<x14>343.759452</x14>
			<y14>348.091993</y14>
			<x15>347.734401</x15>
			<y15>348.556115</y15>
			<x16>357.185403</x16>
			<y16>355.424906</y16>
			<x17>382.449985</x17>
			<y17>341.603141</y17>
			<x18>382.715277</x18>
			<y18>338.489422</y18>
			<x19>335.287835</x19>
			<y19>259.051375</y19>
		</polygon>
	</object>
</annotation>
