<annotation>
	<folder></folder>
	<filename>IMG-20231113-WA0175_rotated_jpg.rf.46455db5de5c069dd2e95b8593732d9a.jpg</filename>
	<path>IMG-20231113-WA0175_rotated_jpg.rf.46455db5de5c069dd2e95b8593732d9a.jpg</path>
	<source>
		<database>roboflow.com</database>
	</source>
	<size>
		<width>640</width>
		<height>640</height>
		<depth>3</depth>
	</size>
	<segmented>0</segmented>
	<object>
		<name>id</name>
		<pose>Unspecified</pose>
		<truncated>0</truncated>
		<difficult>0</difficult>
		<occluded>0</occluded>
		<bndbox>
			<xmin>30</xmin>
			<xmax>561</xmax>
			<ymin>1</ymin>
			<ymax>606</ymax>
		</bndbox>
		<polygon>
			<x1>335.605161</x1>
			<y1>0</y1>
			<x2>332.52259</x2>
			<y2>3.445331</y2>
			<x3>281.295954</x3>
			<y3>73.630838</y3>
			<x4>186.615716</x4>
			<y4>210.997792</y4>
			<x5>121.964236</x5>
			<y5>300.308688</y5>
			<x6>54.222114</x6>
			<y6>400.462771</y6>
			<x7>30.287317</x7>
			<y7>437.587028</y7>
			<x8>29.139934</x8>
			<y8>447.679199</y8>
			<x9>35.147679</x9>
			<y9>459.294445</y9>
			<x10>209.353478</x10>
			<y10>595.664471</y10>
			<x11>224.19432</x11>
			<y11>604.938058</y11>
			<x12>236.119166</x12>
			<y12>603.545691</y12>
			<x13>251.84099</x13>
			<y13>587.820911</y13>
			<x14>384.499883</x14>
			<y14>401.469653</y14>
			<x15>394.568792</x15>
			<y15>390.07373</y15>
			<x16>538.179794</x16>
			<y16>190.913134</y16>
			<x17>556.903829</x17>
			<y17>163.307264</y17>
			<x18>560.082902</x18>
			<y18>153.501985</y18>
			<x19>559.287025</x19>
			<y19>144.160828</y19>
			<x20>538.438438</x20>
			<y20>123.271995</y20>
			<x21>384.550644</x21>
			<y21>1.563363</y21>
			<x22>382.04874</x22>
			<y22>0</y22>
			<x23>335.605161</x23>
			<y23>0</y23>
		</polygon>
	</object>
</annotation>
