<annotation>
	<folder></folder>
	<filename>IMG-20231114-WA0075_jpg.rf.87c489d289125f93e4a9e693ffcca362.jpg</filename>
	<path>IMG-20231114-WA0075_jpg.rf.87c489d289125f93e4a9e693ffcca362.jpg</path>
	<source>
		<database>roboflow.com</database>
	</source>
	<size>
		<width>640</width>
		<height>640</height>
		<depth>3</depth>
	</size>
	<segmented>0</segmented>
	<object>
		<name>id</name>
		<pose>Unspecified</pose>
		<truncated>0</truncated>
		<difficult>0</difficult>
		<occluded>0</occluded>
		<bndbox>
			<xmin>212</xmin>
			<xmax>431</xmax>
			<ymin>227</ymin>
			<ymax>540</ymax>
		</bndbox>
		<polygon>
			<x1>339.681457</x1>
			<y1>528.782043</y1>
			<x2>340.812152</x2>
			<y2>530.531845</y2>
			<x3>353.281702</x3>
			<y3>531.4038</y3>
			<x4>354.412397</x4>
			<y4>533.153603</y4>
			<x5>366.881947</x5>
			<y5>534.025559</y5>
			<x6>368.012641</x6>
			<y6>535.775362</y6>
			<x7>384.223057</x7>
			<y7>536.908904</y7>
			<x8>385.191886</x8>
			<y8>538.408212</y8>
			<x9>394.992064</x9>
			<y9>538.750442</y9>
			<x10>399.302779</x10>
			<y10>536.292645</y10>
			<x11>401.580124</x11>
			<y11>530.604315</y11>
			<x12>402.742731</x12>
			<y12>513.978247</y12>
			<x13>404.105948</x13>
			<y13>512.402835</y13>
			<x14>404.919773</x14>
			<y14>500.764588</y14>
			<x15>407.994988</x15>
			<y15>492.625946</y15>
			<x16>409.622638</x16>
			<y16>469.349452</y16>
			<x17>410.985855</x17>
			<y17>467.774039</y17>
			<x18>415.520025</x18>
			<y18>402.932377</y18>
			<x19>416.88324</x19>
			<y19>401.356966</y19>
			<x20>427.298841</x20>
			<y20>279.286163</y20>
			<x21>429.370156</x21>
			<y21>253.995306</y21>
			<x22>430.324031</x22>
			<y22>226.679886</y22>
			<x23>426.031367</x23>
			<y23>225.733964</y23>
			<x24>413.213033</x24>
			<y24>229.849829</y24>
			<x25>410.486601</x25>
			<y25>233.000651</y25>
			<x26>402.88861</x26>
			<y26>234.140084</y26>
			<x27>399.480571</x27>
			<y27>238.078613</y27>
			<x28>399.131789</x28>
			<y28>243.066433</y28>
			<x29>401.160655</x29>
			<y29>249.891251</y29>
			<x30>398.434224</x30>
			<y30>253.042073</y30>
			<x31>398.085441</x31>
			<y31>258.029893</y31>
			<x32>393.530751</x32>
			<y32>269.406554</y32>
			<x33>384.786108</x33>
			<y33>277.98412</y33>
			<x34>374.345425</x34>
			<y34>283.936981</y34>
			<x35>355.176055</x35>
			<y35>289.279476</y35>
			<x36>344.735372</x36>
			<y36>295.232337</y36>
			<x37>328.292434</x37>
			<y37>297.424008</y37>
			<x38>323.072092</x38>
			<y38>300.400439</y38>
			<x39>315.590362</x39>
			<y39>299.877266</y39>
			<x40>309.006805</x40>
			<y40>304.429108</y40>
			<x41>296.304732</x41>
			<y41>306.882365</y41>
			<x42>292.331346</x42>
			<y42>309.945992</y42>
			<x43>273.394498</x43>
			<y43>311.963272</y43>
			<x44>260.576165</x44>
			<y44>316.079136</y44>
			<x45>231.779938</x45>
			<y45>315.736245</y45>
			<x46>226.776161</x46>
			<y46>324.575396</y46>
			<x47>224.450945</x47>
			<y47>357.827533</y47>
			<x48>223.087729</x48>
			<y48>359.402943</y48>
			<x49>219.134862</x49>
			<y49>415.931572</y49>
			<x50>217.771647</x50>
			<y50>417.506984</y50>
			<x51>211.176695</x51>
			<y51>493.899698</y51>
			<x52>213.205562</x52>
			<y52>500.724516</y52>
			<x53>218.409947</x53>
			<y53>506.936021</y53>
			<x54>224.528462</x54>
			<y54>509.034605</y54>
			<x55>312.480968</x55>
			<y55>523.538526</y55>
			<x56>320.977131</x56>
			<y56>527.474109</y56>
			<x57>339.681457</x57>
			<y57>528.782043</y57>
		</polygon>
	</object>
</annotation>
