<annotation>
	<folder></folder>
	<filename>IMG-20231114-WA0041_jpg.rf.7c6eb34c082b749cac5f9dc3ec35d66c.jpg</filename>
	<path>IMG-20231114-WA0041_jpg.rf.7c6eb34c082b749cac5f9dc3ec35d66c.jpg</path>
	<source>
		<database>roboflow.com</database>
	</source>
	<size>
		<width>640</width>
		<height>640</height>
		<depth>3</depth>
	</size>
	<segmented>0</segmented>
	<object>
		<name>id</name>
		<pose>Unspecified</pose>
		<truncated>0</truncated>
		<difficult>0</difficult>
		<occluded>0</occluded>
		<bndbox>
			<xmin>246</xmin>
			<xmax>402</xmax>
			<ymin>167</ymin>
			<ymax>411</ymax>
		</bndbox>
		<polygon>
			<x1>347.336152</x1>
			<y1>406.010042</y1>
			<x2>400.572478</x2>
			<y2>197.645233</y2>
			<x3>396.403861</x3>
			<y3>190.696058</y3>
			<x4>303.370579</x4>
			<y4>165.796618</y4>
			<x5>297.795496</x5>
			<y5>170.496284</y5>
			<x6>287.29778</x6>
			<y6>215.966886</y6>
			<x7>285.704899</x7>
			<y7>217.309648</y7>
			<x8>274.457346</x8>
			<y8>266.028151</y8>
			<x9>272.864466</x9>
			<y9>267.370912</y9>
			<x10>244.934088</x10>
			<y10>377.237142</y10>
			<x11>247.884742</x11>
			<y11>383.905128</y11>
			<x12>260.064367</x12>
			<y12>386.717016</y12>
			<x13>260.907412</x13>
			<y13>388.622155</y13>
			<x14>327.941957</x14>
			<y14>406.66406</y14>
			<x15>340.543106</x15>
			<y15>410.428517</y15>
			<x16>347.336152</x16>
			<y16>406.010042</y16>
		</polygon>
	</object>
	<object>
		<name>id</name>
		<pose>Unspecified</pose>
		<truncated>0</truncated>
		<difficult>0</difficult>
		<occluded>0</occluded>
		<bndbox>
			<xmin>538</xmin>
			<xmax>641</xmax>
			<ymin>242</ymin>
			<ymax>479</ymax>
		</bndbox>
		<polygon>
			<x1>640</x1>
			<y1>252.091502</y1>
			<x2>597.962665</x2>
			<y2>240.827632</y2>
			<x3>592.718593</x3>
			<y3>244.94396</y3>
			<x4>536.813679</x4>
			<y4>453.583939</y4>
			<x5>539.180608</x5>
			<y5>459.480809</y5>
			<x6>608.784764</x6>
			<y6>478.131186</y6>
			<x7>640</x7>
			<y7>360.340892</y7>
			<x8>640</x8>
			<y8>252.091502</y8>
		</polygon>
	</object>
</annotation>
