<annotation>
	<folder></folder>
	<filename>IMG-20231114-WA0081_jpg.rf.fdebdb22b905cfa4da912e564bb70d6f.jpg</filename>
	<path>IMG-20231114-WA0081_jpg.rf.fdebdb22b905cfa4da912e564bb70d6f.jpg</path>
	<source>
		<database>roboflow.com</database>
	</source>
	<size>
		<width>640</width>
		<height>640</height>
		<depth>3</depth>
	</size>
	<segmented>0</segmented>
	<object>
		<name>id</name>
		<pose>Unspecified</pose>
		<truncated>0</truncated>
		<difficult>0</difficult>
		<occluded>0</occluded>
		<bndbox>
			<xmin>230</xmin>
			<xmax>394</xmax>
			<ymin>314</ymin>
			<ymax>439</ymax>
		</bndbox>
		<polygon>
			<x1>233.173178</x1>
			<y1>321.300675</y1>
			<x2>229.733421</x2>
			<y2>365.200909</y2>
			<x3>231.54091</x3>
			<y3>382.106395</y3>
			<x4>228.611709</x4>
			<y4>414.645309</y4>
			<x5>231.867032</x5>
			<y5>419.734965</y5>
			<x6>240.746026</x6>
			<y6>422.097565</y6>
			<x7>296.388333</x7>
			<y7>428.456448</y7>
			<x8>298.26289</x8>
			<y8>427.547429</y8>
			<x9>327.950217</x9>
			<y9>432.044666</y9>
			<x10>351.570385</x10>
			<y10>432.815774</y10>
			<x11>379.621666</x11>
			<y11>436.994994</y11>
			<x12>381.496222</x12>
			<y12>436.085975</y12>
			<x13>389.67645</x13>
			<y13>437.676051</y13>
			<x14>392.488284</x14>
			<y14>436.312522</y14>
			<x15>392.965307</x15>
			<y15>433.858453</y15>
			<x16>384.375125</x16>
			<y16>416.907941</y16>
			<x17>379.057033</x17>
			<y17>400.593459</y17>
			<x18>371.148851</x18>
			<y18>388.869097</y18>
			<x19>358.638111</x19>
			<y19>357.14915</y19>
			<x20>351.650441</x20>
			<y20>349.423905</y20>
			<x21>348.888906</x21>
			<y21>337.426554</y21>
			<x22>342.156513</x22>
			<y22>324.020649</y22>
			<x23>250.742955</x23>
			<y23>313.892029</y23>
			<x24>248.868398</x24>
			<y24>314.801047</y24>
			<x25>240.688172</x25>
			<y25>313.210972</y25>
			<x26>234.365735</x26>
			<y26>315.165505</y26>
			<x27>231.775644</x27>
			<y27>319.755625</y27>
			<x28>233.173178</x28>
			<y28>321.300675</y28>
		</polygon>
	</object>
	<object>
		<name>id</name>
		<pose>Unspecified</pose>
		<truncated>0</truncated>
		<difficult>0</difficult>
		<occluded>0</occluded>
		<bndbox>
			<xmin>53</xmin>
			<xmax>300</xmax>
			<ymin>386</ymin>
			<ymax>597</ymax>
		</bndbox>
		<polygon>
			<x1>110.91265</x1>
			<y1>405.087833</y1>
			<x2>99.440051</x2>
			<y2>411.237949</y2>
			<x3>98.503535</x3>
			<y3>413.55591</y3>
			<x4>55.844288</x4>
			<y4>443.50635</y4>
			<x5>52.894207</x5>
			<y5>446.358944</y5>
			<x6>52.098222</x6>
			<y6>452.778187</y6>
			<x7>202.719749</x7>
			<y7>593.849256</y7>
			<x8>209.907757</x8>
			<y8>596.079316</y8>
			<x9>223.393919</x9>
			<y9>589.394564</y9>
			<x10>229.762339</x10>
			<y10>582.530394</y10>
			<x11>247.603359</x11>
			<y11>569.516106</y11>
			<x12>251.630487</x12>
			<y12>568.446836</y12>
			<x13>260.948989</x13>
			<y13>558.73007</y13>
			<x14>264.976119</x14>
			<y14>557.660799</y14>
			<x15>280.803573</x15>
			<y15>545.181147</y15>
			<x16>292.27617</x16>
			<y16>539.031031</y16>
			<x17>298.176333</x17>
			<y17>533.32584</y17>
			<x18>298.50406</x18>
			<y18>528.065577</y18>
			<x19>292.112036</x19>
			<y19>519.416273</y19>
			<x20>289.021424</x20>
			<y20>518.167586</y20>
			<x21>276.377908</x21>
			<y21>504.970263</y21>
			<x22>258.630216</x22>
			<y22>491.058887</y22>
			<x23>253.853766</x23>
			<y23>485.084571</y23>
			<x24>248.140798</x24>
			<y24>481.428214</y24>
			<x25>172.560772</x25>
			<y25>410.446849</y25>
			<x26>169.470159</x26>
			<y26>409.19816</y26>
			<x27>147.414275</x27>
			<y27>388.153488</y27>
			<x28>139.687742</x28>
			<y28>385.031766</y28>
			<x29>129.690185</x29>
			<y29>389.755586</y29>
			<x30>110.91265</x30>
			<y30>405.087833</y30>
		</polygon>
	</object>
	<object>
		<name>id</name>
		<pose>Unspecified</pose>
		<truncated>0</truncated>
		<difficult>0</difficult>
		<occluded>0</occluded>
		<bndbox>
			<xmin>217</xmin>
			<xmax>423</xmax>
			<ymin>468</ymin>
			<ymax>616</ymax>
		</bndbox>
		<polygon>
			<x1>375.378721</x1>
			<y1>500.939732</y1>
			<x2>373.668678</x2>
			<y2>498.4692</y2>
			<x3>362.025603</x3>
			<y3>499.922621</y3>
			<x4>356.982734</x4>
			<y4>497.510264</y4>
			<x5>348.65067</x5>
			<y5>497.655701</y5>
			<x6>342.763686</x6>
			<y6>494.632982</y6>
			<x7>347.741109</x7>
			<y7>493.295911</y7>
			<x8>345.186951</x8>
			<y8>490.215018</y8>
			<x9>338.5213</x9>
			<y9>490.331366</y9>
			<x10>326.790964</x10>
			<y10>486.78555</y10>
			<x11>306.750378</x11>
			<y11>484.634978</y11>
			<x12>300.01928</x12>
			<y12>481.001898</y12>
			<x13>293.35363</x13>
			<y13>481.118248</y13>
			<x14>268.24836</x14>
			<y14>475.30551</y14>
			<x15>261.582708</x15>
			<y15>475.421859</y15>
			<x16>253.185198</x16>
			<y16>471.817867</y16>
			<x17>233.144613</x17>
			<y17>469.667297</y17>
			<x18>228.101743</x18>
			<y18>467.254939</y18>
			<x19>216.436853</x19>
			<y19>467.458551</y19>
			<x20>215.658186</x20>
			<y20>470.597619</y20>
			<x21>219.900571</x21>
			<y21>474.899233</y21>
			<x22>228.232636</x22>
			<y22>474.753797</y22>
			<x23>238.318376</x23>
			<y23>479.578511</y23>
			<x24>241.651201</x24>
			<y24>479.520337</y24>
			<x25>248.404114</x25>
			<y25>484.403225</y25>
			<x26>260.090819</x26>
			<y26>485.449424</y26>
			<x27>273.553016</x27>
			<y27>492.715583</y27>
			<x28>283.573308</x28>
			<y28>493.790868</y28>
			<x29>297.013687</x29>
			<y29>499.807218</y29>
			<x30>299.589661</x30>
			<y30>504.13792</y30>
			<x31>298.075956</x31>
			<y31>512.915675</y31>
			<x32>291.519383</x32>
			<y32>519.281073</y32>
			<x33>291.58483</x33>
			<y33>523.030501</y33>
			<x34>275.313381</x34>
			<y34>545.817948</y34>
			<x35>272.089633</x35>
			<y35>552.12517</y35>
			<x36>272.176895</x36>
			<y36>557.124409</y36>
			<x37>265.598505</x37>
			<y37>562.239997</y37>
			<x38>264.04117</x38>
			<y38>568.518133</y38>
			<x39>257.506412</x39>
			<y39>576.133339</y39>
			<x40>255.949076</x40>
			<y40>582.411475</y40>
			<x41>252.659882</x41>
			<y41>584.969269</y41>
			<x42>252.790775</x42>
			<y42>592.468127</y42>
			<x43>272.009061</x43>
			<y43>595.258147</y43>
			<x44>283.739397</x44>
			<y44>598.803963</y44>
			<x45>292.071461</x45>
			<y45>598.658527</y45>
			<x46>298.780744</x46>
			<y46>601.041797</y46>
			<x47>318.821329</x47>
			<y47>603.192368</y47>
			<x48>328.885252</x48>
			<y48>606.767273</y48>
			<x49>343.904783</x49>
			<y49>607.755296</y49>
			<x50>362.322586</x50>
			<y50>612.434574</y50>
			<x51>370.654651</x51>
			<y51>612.289138</y51>
			<x52>377.363933</x52>
			<y52>614.672407</y52>
			<x53>386.518295</x53>
			<y53>613.887522</y53>
			<x54>393.118501</x54>
			<y54>610.021743</y54>
			<x55>394.588573</x55>
			<y55>598.744369</y55>
			<x56>397.855953</x56>
			<y56>594.936766</y56>
			<x57>401.014254</x57>
			<y57>584.880114</y57>
			<x58>400.905176</x58>
			<y58>578.631067</y58>
			<x59>404.194371</x59>
			<y59>576.073272</y59>
			<x60>408.866376</x60>
			<y60>557.238866</y60>
			<x61>412.133757</x61>
			<y61>553.431263</y61>
			<x62>412.024679</x62>
			<y62>547.182215</y62>
			<x63>414.491575</x63>
			<y63>545.263869</y63>
			<x64>418.668514</x64>
			<y64>545.816056</y64>
			<x65>418.559437</x65>
			<y65>539.567008</y65>
			<x66>416.871209</x66>
			<y66>538.346285</y66>
			<x67>418.515805</x67>
			<y67>537.067388</y67>
			<x68>418.341282</x68>
			<y68>527.068912</y68>
			<x69>421.565031</x69>
			<y69>520.761689</y69>
			<x70>419.702278</x70>
			<y70>509.542489</y70>
			<x71>412.10525</x71>
			<y71>504.049239</y71>
			<x72>395.419306</x72>
			<y72>503.090303</y72>
			<x73>393.709263</x73>
			<y73>500.619771</y73>
			<x74>387.021795</x74>
			<y74>499.486311</y74>
			<x75>375.378721</x75>
			<y75>500.939732</y75>
		</polygon>
	</object>
</annotation>
