<annotation>
	<folder></folder>
	<filename>IMG20231112205610-1-_jpg.rf.5b6b090697e2951e46f6e6f44af1142a.jpg</filename>
	<path>IMG20231112205610-1-_jpg.rf.5b6b090697e2951e46f6e6f44af1142a.jpg</path>
	<source>
		<database>roboflow.com</database>
	</source>
	<size>
		<width>640</width>
		<height>640</height>
		<depth>3</depth>
	</size>
	<segmented>0</segmented>
	<object>
		<name>id</name>
		<pose>Unspecified</pose>
		<truncated>0</truncated>
		<difficult>0</difficult>
		<occluded>0</occluded>
		<bndbox>
			<xmin>159</xmin>
			<xmax>504</xmax>
			<ymin>208</ymin>
			<ymax>380</ymax>
		</bndbox>
		<polygon>
			<x1>490.66678</x1>
			<y1>206.770006</y1>
			<x2>440.735304</x2>
			<y2>209.386804</y2>
			<x3>439.136341</x3>
			<y3>210.722317</y3>
			<x4>437.471958</x4>
			<y4>210.809544</y4>
			<x5>435.742155</x5>
			<y5>209.648484</y5>
			<x6>434.077772</x6>
			<y6>209.73571</y6>
			<x7>432.47881</x7>
			<y7>211.071223</y7>
			<x8>424.156897</x8>
			<y8>211.507357</y8>
			<x9>422.427095</x9>
			<y9>210.346296</y9>
			<x10>414.105183</x10>
			<y10>210.782429</y10>
			<x11>412.506219</x11>
			<y11>212.117943</y11>
			<x12>410.776417</x12>
			<y12>210.956882</y12>
			<x13>405.783269</x13>
			<y13>211.218562</y13>
			<x14>404.184306</x14>
			<y14>212.554076</y14>
			<x15>402.454504</x15>
			<y15>211.393015</y15>
			<x16>387.475061</x16>
			<y16>212.178054</y16>
			<x17>385.876099</x17>
			<y17>213.513568</y17>
			<x18>375.889803</x18>
			<y18>214.036928</y18>
			<x19>374.160001</x19>
			<y19>212.875868</y19>
			<x20>370.831236</x20>
			<y20>213.050321</y20>
			<x21>369.232273</x21>
			<y21>214.385834</y21>
			<x22>242.739199</x22>
			<y22>221.015055</y22>
			<x23>241.009396</x23>
			<y23>219.853995</y23>
			<x24>237.680631</x24>
			<y24>220.028448</y24>
			<x25>236.081668</x25>
			<y25>221.363962</y25>
			<x26>167.841983</x26>
			<y26>224.940252</y26>
			<x27>166.243021</x27>
			<y27>226.275766</y27>
			<x28>164.578638</x28>
			<y28>226.362993</y28>
			<x29>163.844577</x29>
			<y29>228.279035</y29>
			<x30>161.380713</x30>
			<y30>229.03402</y30>
			<x31>158.982269</x31>
			<y31>231.03729</y31>
			<x32>159.178529</x32>
			<y32>234.78215</y32>
			<x33>157.579566</x33>
			<y33>236.117664</y33>
			<x34>157.775826</x34>
			<y34>239.862524</y34>
			<x35>159.505629</x35>
			<y35>241.023585</y35>
			<x36>161.729907</x36>
			<y36>283.46534</y36>
			<x37>163.459709</x37>
			<y37>284.6264</y37>
			<x38>163.525129</x38>
			<y38>285.874688</y38>
			<x39>161.926167</x39>
			<y39>287.210201</y39>
			<x40>163.786809</x40>
			<y40>290.867835</y40>
			<x41>162.187847</x41>
			<y41>292.203348</y41>
			<x42>163.917649</x42>
			<y42>293.364409</y42>
			<x43>164.964368</x43>
			<y43>313.337</y43>
			<x44>166.69417</x44>
			<y44>314.49806</y44>
			<x45>168.26425</x45>
			<y45>344.456946</y45>
			<x46>169.994052</x46>
			<y46>345.618007</y46>
			<x47>171.498711</x47>
			<y47>374.328605</y47>
			<x48>173.228512</x48>
			<y48>375.489666</y48>
			<x49>174.158834</x49>
			<y49>377.318483</y49>
			<x50>175.823216</x50>
			<y50>377.231257</y50>
			<x51>180.947204</x51>
			<y51>379.466151</y51>
			<x52>202.584178</x52>
			<y52>378.332204</y52>
			<x53>204.31398</x53>
			<y53>379.493265</y53>
			<x54>224.286571</x54>
			<y54>378.446546</y54>
			<x55>225.885533</x55>
			<y55>377.111032</y55>
			<x56>230.944101</x56>
			<y56>378.097639</y56>
			<x57>232.543064</x57>
			<y57>376.762126</y57>
			<x58>235.871828</x58>
			<y58>376.587673</y58>
			<x59>237.601631</x59>
			<y59>377.748733</y59>
			<x60>244.259162</x60>
			<y60>377.399826</y60>
			<x61>245.988964</x61>
			<y61>378.560887</y61>
			<x62>299.249206</x62>
			<y62>375.769636</y62>
			<x63>300.717328</x63>
			<y63>371.937548</y63>
			<x64>305.775896</x64>
			<y64>372.924156</y64>
			<x65>306.640797</x65>
			<y65>373.504686</y65>
			<x66>305.041835</x66>
			<y66>374.8402</y66>
			<x67>305.906736</x67>
			<y67>375.42073</y67>
			<x68>314.228649</x68>
			<y68>374.984597</y68>
			<x69>315.02813</x69>
			<y69>374.31684</y69>
			<x70>313.298328</x70>
			<y70>373.155779</y70>
			<x71>314.03239</x71>
			<y71>371.239736</y71>
			<x72>319.221797</x72>
			<y72>374.722917</y72>
			<x73>324.214945</x73>
			<y73>374.461237</y73>
			<x74>325.944746</x74>
			<y74>375.622297</y74>
			<x75>377.540606</x75>
			<y75>372.918273</y75>
			<x76>379.270408</x76>
			<y76>374.079333</y76>
			<x77>445.845711</x77>
			<y77>370.590269</y77>
			<x78>447.575513</x78>
			<y78>371.75133</y78>
			<x79>449.174476</x79>
			<y79>370.415816</y79>
			<x80>455.832006</x80>
			<y80>370.06691</y80>
			<x81>457.561809</x81>
			<y81>371.227971</y81>
			<x82>492.513843</x82>
			<y82>369.396212</y82>
			<x83>493.313323</x83>
			<y83>368.728455</y83>
			<x84>495.777188</x84>
			<y84>367.973472</y84>
			<x85>501.373557</x85>
			<y85>363.299175</y85>
			<x86>501.177298</x86>
			<y86>359.554314</y86>
			<x87>502.776259</x87>
			<y87>358.2188</y87>
			<x88>501.00992</x88>
			<y88>324.515054</y88>
			<x89>502.608884</x89>
			<y89>323.17954</y89>
			<x90>502.543464</x90>
			<y90>321.931252</y90>
			<x91>500.81366</x91>
			<y91>320.770193</y91>
			<x92>500.748241</x92>
			<y92>319.521905</y92>
			<x93>502.347204</x93>
			<y93>318.186392</y93>
			<x94>499.403306</x94>
			<y94>262.013481</y94>
			<x95>501.002269</x95>
			<y95>260.677968</y95>
			<x96>499.497611</x96>
			<y96>231.967368</y96>
			<x97>501.096572</x97>
			<y97>230.631855</y97>
			<x98>500.769473</x98>
			<y98>224.39042</y98>
			<x99>499.039671</x99>
			<y99>223.229359</y99>
			<x100>498.516312</x100>
			<y100>213.243064</y100>
			<x101>496.786508</x101>
			<y101>212.082004</y101>
			<x102>496.655669</x102>
			<y102>209.58543</y102>
			<x103>494.060965</x103>
			<y103>207.84384</y103>
			<x104>492.396582</x104>
			<y104>207.931067</y104>
			<x105>490.66678</x105>
			<y105>206.770006</y105>
		</polygon>
	</object>
</annotation>
