<annotation>
	<folder></folder>
	<filename>msg975361832-170634_jpg.rf.bd1d3f045b481f9448ee7880fc1b009d.jpg</filename>
	<path>msg975361832-170634_jpg.rf.bd1d3f045b481f9448ee7880fc1b009d.jpg</path>
	<source>
		<database>roboflow.com</database>
	</source>
	<size>
		<width>640</width>
		<height>640</height>
		<depth>3</depth>
	</size>
	<segmented>0</segmented>
	<object>
		<name>id</name>
		<pose>Unspecified</pose>
		<truncated>0</truncated>
		<difficult>0</difficult>
		<occluded>0</occluded>
		<bndbox>
			<xmin>127</xmin>
			<xmax>571</xmax>
			<ymin>154</ymin>
			<ymax>506</ymax>
		</bndbox>
		<polygon>
			<x1>516.516979</x1>
			<y1>352.084464</y1>
			<x2>520.076874</x2>
			<y2>352.05688</y2>
			<x3>548.744335</x3>
			<y3>338.374611</y3>
			<x4>566.072063</x4>
			<y4>327.706325</y4>
			<x5>569.502129</x5>
			<y5>320.364456</y5>
			<x6>547.575877</x6>
			<y6>272.546043</y6>
			<x7>539.536384</x7>
			<y7>260.903872</y7>
			<x8>540.19643</x8>
			<y8>257.972641</y8>
			<x9>521.217595</x9>
			<y9>231.784652</y9>
			<x10>506.458703</x10>
			<y10>202.637847</y10>
			<x11>487.031907</x11>
			<y11>175.282884</y11>
			<x12>478.308581</x12>
			<y12>157.208555</y12>
			<x13>473.404806</x13>
			<y13>153.735213</y13>
			<x14>467.840983</x14>
			<y14>153.193102</y14>
			<x15>445.055478</x15>
			<y15>161.270172</y15>
			<x16>407.500173</x16>
			<y16>179.703097</y16>
			<x17>384.160662</x17>
			<y17>188.662296</y17>
			<x18>363.720999</x18>
			<y18>200.525141</y18>
			<x19>336.161546</x19>
			<y19>212.443155</y19>
			<x20>327.721662</x20>
			<y20>218.360786</y20>
			<x21>327.615617</x21>
			<y21>220.409889</y21>
			<x22>336.397417</x22>
			<y22>217.708337</y22>
			<x23>339.851269</x23>
			<y23>219.729856</y23>
			<x24>329.301414</x24>
			<y24>227.126895</y24>
			<x25>293.962124</x25>
			<y25>242.031308</y25>
			<x26>287.844298</x26>
			<y26>242.371325</y26>
			<x27>289.506309</x27>
			<y27>239.724942</y27>
			<x28>294.622171</x28>
			<y28>239.100077</y28>
			<x29>294.834258</x29>
			<y29>235.00187</y29>
			<x30>280.830552</x30>
			<y30>240.37739</y30>
			<x31>279.616501</x31>
			<y31>244.190749</y31>
			<x32>283.176396</x32>
			<y32>244.163165</y32>
			<x33>284.072316</x33>
			<y33>246.497116</y33>
			<x34>275.078428</x34>
			<y34>253.296874</y34>
			<x35>243.299033</x35>
			<y35>268.173703</y35>
			<x36>239.739138</x36>
			<y36>268.201287</y36>
			<x37>213.075606</x37>
			<y37>282.453252</y37>
			<x38>211.071678</x38>
			<y38>281.883556</y38>
			<x39>207.299695</x39>
			<y39>286.009348</y39>
			<x40>185.068193</x40>
			<y40>293.20429</y40>
			<x41>179.740243</x41>
			<y41>297.927362</y41>
			<x42>176.180348</x42>
			<y42>297.954946</y42>
			<x43>172.408366</x43>
			<y43>302.080736</y43>
			<x44>161.516594</x44>
			<y44>306.261696</y44>
			<x45>154.632677</x45>
			<y45>311.582046</y45>
			<x46>128.629191</x46>
			<y46>322.90278</y46>
			<x47>125.859173</x47>
			<y47>327.313419</y47>
			<x48>131.658867</x48>
			<y48>333.120713</y48>
			<x49>138.778657</x49>
			<y49>333.065544</y49>
			<x50>152.381972</x50>
			<y50>345.249827</y50>
			<x51>158.393755</x51>
			<y51>346.958913</y51>
			<x52>167.800913</x52>
			<y52>371.465399</y52>
			<x53>170.806804</x53>
			<y53>372.319943</y53>
			<x54>183.254543</x54>
			<y54>367.541704</y54>
			<x55>186.260434</x55>
			<y55>368.396248</y55>
			<x56>169.038749</x56>
			<y56>377.01543</y56>
			<x57>175.604535</x57>
			<y57>377.842389</y57>
			<x58>168.166613</x58>
			<y58>384.044867</y58>
			<x59>162.414489</x59>
			<y59>396.96435</y59>
			<x60>140.630946</x60>
			<y60>405.32627</y60>
			<x61>136.175132</x61>
			<y61>403.019902</y61>
			<x62>131.50723</x62>
			<y62>404.811742</y62>
			<x63>128.313036</x63>
			<y63>417.418794</y63>
			<x64>132.556762</x64>
			<y64>423.823367</y64>
			<x65>127.228814</x65>
			<y65>428.546438</y65>
			<x66>133.900642</x66>
			<y66>427.324294</y66>
			<x67>137.24845</x67>
			<y67>431.394916</y67>
			<x68>140.620041</x68>
			<y68>444.828927</y68>
			<x69>150.663462</x69>
			<y69>457.040794</y69>
			<x70>159.622661</x70>
			<y70>480.380304</y70>
			<x71>164.974397</x71>
			<y71>485.020622</y71>
			<x72>170.349915</x72>
			<y72>499.024329</y72>
			<x73>176.809658</x73>
			<y73>501.900391</y73>
			<x74>176.14961</x74>
			<y74>504.831622</y74>
			<x75>184.271363</x75>
			<y75>505.061301</y75>
			<x76>232.058392</x76>
			<y76>485.378648</y76>
			<x77>261.83386</x77>
			<y77>469.932123</y77>
			<x78>267.161809</x78>
			<y78>465.209053</y78>
			<x79>295.169222</x79>
			<y79>454.458014</y79>
			<x80>343.168338</x80>
			<y80>430.677154</y80>
			<x81>349.156335</x81>
			<y81>423.022853</y81>
			<x82>355.828164</x82>
			<y82>421.800709</y82>
			<x83>354.142369</x83>
			<y83>415.083704</y83>
			<x84>357.360347</x84>
			<y84>411.84004</y84>
			<x85>364.480137</x85>
			<y85>411.784871</y85>
			<x86>379.59185</x86>
			<y86>404.645097</y86>
			<x87>384.495625</x87>
			<y87>408.118439</y87>
			<x88>391.827502</x88>
			<y88>403.965064</y88>
			<x89>408.283096</x89>
			<y89>400.326216</y89>
			<x90>490.513494</x90>
			<y90>363.405198</y90>
			<x91>495.629357</x91>
			<y91>362.780334</y91>
			<x92>516.516979</x92>
			<y92>352.084464</y92>
		</polygon>
	</object>
</annotation>
