<annotation>
	<folder></folder>
	<filename>msg975361832-170645_jpg.rf.9d42ee575bdac93a7021723a2c5ad6b6.jpg</filename>
	<path>msg975361832-170645_jpg.rf.9d42ee575bdac93a7021723a2c5ad6b6.jpg</path>
	<source>
		<database>roboflow.com</database>
	</source>
	<size>
		<width>640</width>
		<height>640</height>
		<depth>3</depth>
	</size>
	<segmented>0</segmented>
	<object>
		<name>id</name>
		<pose>Unspecified</pose>
		<truncated>0</truncated>
		<difficult>0</difficult>
		<occluded>0</occluded>
		<bndbox>
			<xmin>194</xmin>
			<xmax>461</xmax>
			<ymin>50</ymin>
			<ymax>624</ymax>
		</bndbox>
		<polygon>
			<x1>201.518609</x1>
			<y1>286.963418</y1>
			<x2>201.169614</x2>
			<y2>296.957326</y2>
			<x3>202.898057</x3>
			<y3>301.18689</y3>
			<x4>206.050237</x4>
			<y4>300.463126</y4>
			<x5>205.280203</x5>
			<y5>304.605443</y5>
			<x6>200.878785</x6>
			<y6>305.285582</y6>
			<x7>199.16422</x7>
			<y7>318.567169</y7>
			<x8>200.006297</x8>
			<y8>330.270353</y8>
			<x9>202.388443</x9>
			<y9>333.688905</y9>
			<x10>197.76824</x10>
			<y10>358.542802</y10>
			<x11>194.452788</x11>
			<y11>453.484931</y11>
			<x12>195.90428</x12>
			<y12>483.553904</y12>
			<x13>194.422378</x13>
			<y13>490.172885</y13>
			<x14>192.907413</x14>
			<y14>605.19008</y14>
			<x15>201.898624</x15>
			<y15>616.343996</y15>
			<x16>395.530597</x16>
			<y16>623.105773</y16>
			<x17>406.948241</x17>
			<y17>618.501438</y17>
			<x18>425.803151</x18>
			<y18>615.824502</y18>
			<x19>451.920828</x19>
			<y19>620.071916</y19>
			<x20>459.111553</x20>
			<y20>611.150768</y20>
			<x21>460.230582</x21>
			<y21>597.014543</y21>
			<x22>456.679202</x22>
			<y22>394.267093</y22>
			<x23>452.064306</x23>
			<y23>275.700475</y23>
			<x24>450.792618</x24>
			<y24>97.214031</y24>
			<x25>448.32455</x25>
			<y25>60.438828</y25>
			<x26>442.964723</x26>
			<y26>52.747087</y26>
			<x27>434.336385</x27>
			<y27>49.110414</y27>
			<x28>370.334391</x28>
			<y28>55.213828</y28>
			<x29>309.905615</x29>
			<y29>66.445069</y29>
			<x30>290.876208</x30>
			<y30>74.11896</y30>
			<x31>265.71694</x31>
			<y31>78.243427</y31>
			<x32>210.11062</x32>
			<y32>94.64612</y32>
			<x33>204.2273</x33>
			<y33>101.945242</y33>
			<x34>201.379829</x34>
			<y34>111.851901</y34>
			<x35>200.449176</x35>
			<y35>138.502322</y35>
			<x36>198.585215</x36>
			<y36>263.513425</y36>
			<x37>201.983936</x37>
			<y37>273.638206</y37>
			<x38>199.252795</x38>
			<y38>280.213563</y38>
			<x39>201.518609</x39>
			<y39>286.963418</y39>
		</polygon>
	</object>
</annotation>
