<annotation>
	<folder></folder>
	<filename>msg975361832-170688-1-_jpg.rf.bac9dcbe4e42fe6a31e156c6f2e1f1cf.jpg</filename>
	<path>msg975361832-170688-1-_jpg.rf.bac9dcbe4e42fe6a31e156c6f2e1f1cf.jpg</path>
	<source>
		<database>roboflow.com</database>
	</source>
	<size>
		<width>640</width>
		<height>640</height>
		<depth>3</depth>
	</size>
	<segmented>0</segmented>
	<object>
		<name>id</name>
		<pose>Unspecified</pose>
		<truncated>0</truncated>
		<difficult>0</difficult>
		<occluded>0</occluded>
		<bndbox>
			<xmin>182</xmin>
			<xmax>498</xmax>
			<ymin>159</ymin>
			<ymax>638</ymax>
		</bndbox>
		<polygon>
			<x1>217.957347</x1>
			<y1>479.005932</y1>
			<x2>210.394665</x2>
			<y2>487.240363</y2>
			<x3>180.533952</x3>
			<y3>591.377046</y3>
			<x4>185.163651</x4>
			<y4>597.906088</y4>
			<x5>181.841705</x5>
			<y5>600.421201</y5>
			<x6>193.769172</x6>
			<y6>606.442096</y6>
			<x7>307.176816</x7>
			<y7>637.227382</y7>
			<x8>254.024637</x8>
			<y8>618.518575</y8>
			<x9>247.557356</x9>
			<y9>618.397944</y9>
			<x10>246.444084</x10>
			<y10>615.477969</y10>
			<x11>262.152892</x11>
			<y11>617.381649</y11>
			<x12>315.022284</x12>
			<y12>632.541703</y12>
			<x13>319.174716</x13>
			<y13>629.397814</y13>
			<x14>318.149748</x14>
			<y14>623.902412</y14>
			<x15>321.100604</x15>
			<y15>620.413975</y15>
			<x16>327.108489</x16>
			<y16>622.136708</y16>
			<x17>330.430435</x17>
			<y17>619.621597</y17>
			<x18>337.180501</x18>
			<y18>623.290979</y18>
			<x19>340.767361</x19>
			<y19>613.049584</y19>
			<x20>343.258821</x20>
			<y20>611.16325</y20>
			<x21>350.008888</x21>
			<y21>614.832633</y21>
			<x22>366.265396</x22>
			<y22>612.558782</y22>
			<x23>373.474858</x23>
			<y23>614.626062</y23>
			<x24>374.110864</x24>
			<y24>607.873104</y24>
			<x25>380.118749</x25>
			<y25>609.595837</y25>
			<x26>382.168684</x26>
			<y26>620.586641</y26>
			<x27>397.32979</x27>
			<y27>626.667851</y27>
			<x28>399.556335</x28>
			<y28>632.507799</y28>
			<x29>402.50719</x29>
			<y29>629.019363</y29>
			<x30>406.270659</x30>
			<y30>613.627112</y30>
			<x31>429.858573</x31>
			<y31>515.493978</y31>
			<x32>446.537681</x32>
			<y32>430.117351</y32>
			<x33>460.955554</x33>
			<y33>375.301308</y33>
			<x34>472.687487</x34>
			<y34>316.247419</y34>
			<x35>481.416003</x35>
			<y35>285.807466</y35>
			<x36>483.606805</x36>
			<y36>269.097344</y36>
			<x37>497.282496</x37>
			<y37>212.334652</y37>
			<x38>491.539525</x38>
			<y38>202.885636</y38>
			<x39>388.203893</x39>
			<y39>173.25462</y39>
			<x40>345.972085</x40>
			<y40>166.346341</y40>
			<x41>317.134233</x41>
			<y41>158.07722</y41>
			<x42>307.345006</x42>
			<y42>160.471702</y42>
			<x43>299.69402</x43>
			<y43>171.28156</y43>
			<x44>290.046712</x44>
			<y44>204.925719</y44>
			<x45>280.505581</x45>
			<y45>247.269486</y45>
			<x46>219.865363</x46>
			<y46>458.747059</y46>
			<x47>219.79493</x47>
			<y47>472.597521</y47>
			<x48>217.957347</x48>
			<y48>479.005932</y48>
		</polygon>
	</object>
</annotation>
