<annotation>
	<folder></folder>
	<filename>WhatsApp-Image-2023-11-11-at-3-52-36-PM_jpeg_jpg.rf.026f0449bf3608869b0d4a459ac26c21.jpg</filename>
	<path>WhatsApp-Image-2023-11-11-at-3-52-36-PM_jpeg_jpg.rf.026f0449bf3608869b0d4a459ac26c21.jpg</path>
	<source>
		<database>roboflow.com</database>
	</source>
	<size>
		<width>640</width>
		<height>640</height>
		<depth>3</depth>
	</size>
	<segmented>0</segmented>
	<object>
		<name>id</name>
		<pose>Unspecified</pose>
		<truncated>0</truncated>
		<difficult>0</difficult>
		<occluded>0</occluded>
		<bndbox>
			<xmin>99</xmin>
			<xmax>574</xmax>
			<ymin>139</ymin>
			<ymax>399</ymax>
		</bndbox>
		<polygon>
			<x1>267.128087</x1>
			<y1>149.035863</y1>
			<x2>182.152317</x2>
			<y2>143.6397</y2>
			<x3>145.758958</x3>
			<y3>139.171157</y3>
			<x4>127.409942</x4>
			<y4>138.177568</y4>
			<x5>117.027471</x5>
			<y5>140.680924</y5>
			<x6>112.206347</x6>
			<y6>145.756207</y6>
			<x7>108.571726</x7>
			<y7>161.681966</y7>
			<x8>109.595163</x8>
			<y8>180.698438</y8>
			<x9>104.068123</x9>
			<y9>253.064264</y9>
			<x10>106.614926</x10>
			<y10>259.673909</y10>
			<x11>98.236409</x11>
			<y11>327.911457</y11>
			<x12>99.56452</x12>
			<y12>344.446563</y12>
			<x13>104.668857</x13>
			<y13>350.740539</y13>
			<x14>110.230204</x14>
			<y14>353.312469</y14>
			<x15>167.225439</x15>
			<y15>360.940297</y15>
			<x16>217.15742</x16>
			<y16>364.552399</y16>
			<x17>289.944139</x17>
			<y17>373.489484</y17>
			<x18>510.720218</x18>
			<y18>394.300441</y18>
			<x19>515.530613</x19>
			<y19>396.150471</y19>
			<x20>540.496603</x20>
			<y20>397.956522</y20>
			<x21>554.187562</x21>
			<y21>395.859399</y21>
			<x22>560.815267</x22>
			<y22>389.746548</y22>
			<x23>562.338633</x23>
			<y23>377.339721</y23>
			<x24>562.838564</x24>
			<y24>345.916423</y24>
			<x25>567.10399</x25>
			<y25>311.177308</y25>
			<x26>564.861859</x26>
			<y26>302.086298</y26>
			<x27>566.973113</x27>
			<y27>298.567365</y27>
			<x28>564.316893</x28>
			<y28>265.497152</y28>
			<x29>565.121496</x29>
			<y29>231.592489</y29>
			<x30>572.543073</x30>
			<y30>198.500288</y30>
			<x31>572.869207</x31>
			<y31>182.168297</y31>
			<x32>565.958289</x32>
			<y32>176.911887</y32>
			<x33>556.185165</x33>
			<y33>174.452511</y33>
			<x34>509.714007</x34>
			<y34>170.005958</y34>
			<x35>343.527964</x35>
			<y35>155.897814</y35>
			<x36>328.335099</x36>
			<y36>156.55114</y36>
			<x37>267.128087</x37>
			<y37>149.035863</y37>
		</polygon>
	</object>
</annotation>
