<annotation>
	<folder></folder>
	<filename>WhatsApp-Image-2023-10-19-at-2-43-16-PM_jpeg_jpg.rf.4c69945c0ec43d2576ed15b7bd7b63a1.jpg</filename>
	<path>WhatsApp-Image-2023-10-19-at-2-43-16-PM_jpeg_jpg.rf.4c69945c0ec43d2576ed15b7bd7b63a1.jpg</path>
	<source>
		<database>roboflow.com</database>
	</source>
	<size>
		<width>640</width>
		<height>640</height>
		<depth>3</depth>
	</size>
	<segmented>0</segmented>
	<object>
		<name>id</name>
		<pose>Unspecified</pose>
		<truncated>0</truncated>
		<difficult>0</difficult>
		<occluded>0</occluded>
		<bndbox>
			<xmin>134</xmin>
			<xmax>510</xmax>
			<ymin>191</ymin>
			<ymax>500</ymax>
		</bndbox>
		<polygon>
			<x1>133.853125</x1>
			<y1>490.966667</y1>
			<x2>141.353125</x2>
			<y2>499.3</y2>
			<x3>494.478125</x3>
			<y3>498.466667</y3>
			<x4>505.728125</x4>
			<y4>491.8</y4>
			<x5>508.853125</x5>
			<y5>484.3</y5>
			<x6>508.853125</x6>
			<y6>455.966667</y6>
			<x7>507.603125</x7>
			<y7>454.3</y7>
			<x8>508.853125</x8>
			<y8>450.966667</y8>
			<x9>507.603125</x9>
			<y9>449.3</y9>
			<x10>507.603125</x10>
			<y10>417.633333</y10>
			<x11>506.353125</x11>
			<y11>415.966667</y11>
			<x12>507.603125</x12>
			<y12>412.633333</y12>
			<x13>506.353125</x13>
			<y13>410.966667</y13>
			<x14>506.353125</x14>
			<y14>384.3</y14>
			<x15>505.103125</x15>
			<y15>382.633333</y15>
			<x16>506.353125</x16>
			<y16>379.3</y16>
			<x17>505.103125</x17>
			<y17>377.633333</y17>
			<x18>505.103125</x18>
			<y18>315.966667</y18>
			<x19>503.853125</x19>
			<y19>314.3</y19>
			<x20>503.853125</x20>
			<y20>284.3</y20>
			<x21>502.603125</x21>
			<y21>282.633333</y21>
			<x22>502.603125</x22>
			<y22>232.633333</y22>
			<x23>501.353125</x23>
			<y23>230.966667</y23>
			<x24>501.353125</x24>
			<y24>205.966667</y24>
			<x25>498.853125</x25>
			<y25>197.633333</y25>
			<x26>491.978125</x26>
			<y26>190.133333</y26>
			<x27>148.228125</x27>
			<y27>190.133333</y27>
			<x28>145.728125</x28>
			<y28>191.8</y28>
			<x29>141.353125</x29>
			<y29>197.633333</y29>
			<x30>138.853125</x30>
			<y30>205.966667</y30>
			<x31>135.103125</x31>
			<y31>417.633333</y31>
			<x32>133.853125</x32>
			<y32>419.3</y32>
			<x33>133.853125</x33>
			<y33>454.3</y33>
			<x34>132.603125</x34>
			<y34>455.966667</y34>
			<x35>132.603125</x35>
			<y35>485.966667</y35>
			<x36>133.853125</x36>
			<y36>490.966667</y36>
		</polygon>
	</object>
</annotation>
