<annotation>
	<folder></folder>
	<filename>WhatsApp-Image-2023-10-24-at-1-16-57-PM-1-_jpeg_jpg.rf.e8e01a4a0dc431cc39a0342c4f561a78.jpg</filename>
	<path>WhatsApp-Image-2023-10-24-at-1-16-57-PM-1-_jpeg_jpg.rf.e8e01a4a0dc431cc39a0342c4f561a78.jpg</path>
	<source>
		<database>roboflow.com</database>
	</source>
	<size>
		<width>640</width>
		<height>640</height>
		<depth>3</depth>
	</size>
	<segmented>0</segmented>
	<object>
		<name>id</name>
		<pose>Unspecified</pose>
		<truncated>0</truncated>
		<difficult>0</difficult>
		<occluded>0</occluded>
		<bndbox>
			<xmin>58</xmin>
			<xmax>472</xmax>
			<ymin>166</ymin>
			<ymax>535</ymax>
		</bndbox>
		<polygon>
			<x1>421.981535</x1>
			<y1>518.745269</y1>
			<x2>423.501959</x2>
			<y2>517.320983</y2>
			<x3>423.13919</x3>
			<y3>512.179884</y3>
			<x4>424.659613</x4>
			<y4>510.755597</y4>
			<x5>424.586258</x5>
			<y5>503.973153</y5>
			<x6>426.106681</x6>
			<y6>502.548866</y6>
			<x7>425.454499</x7>
			<y7>499.049114</y7>
			<x8>427.264336</x8>
			<y8>495.983481</y8>
			<x9>426.612154</x9>
			<y9>492.483728</y9>
			<x10>428.059222</x10>
			<y10>484.276998</y10>
			<x11>429.579645</x11>
			<y11>482.852711</y11>
			<x12>428.927463</x12>
			<y12>479.352959</y12>
			<x13>431.026713</x13>
			<y13>474.645981</y13>
			<x14>430.085118</x14>
			<y14>472.787574</y14>
			<x15>431.605541</x15>
			<y15>471.363287</y15>
			<x16>431.242772</x16>
			<y16>466.222188</y16>
			<x17>433.342022</x17>
			<y17>461.515209</y17>
			<x18>432.400426</x18>
			<y18>459.656804</y18>
			<x19>433.920849</x19>
			<y19>458.232518</y19>
			<x20>433.55808</x20>
			<y20>453.091418</y20>
			<x21>437.972641</x21>
			<y21>435.25367</y21>
			<x22>437.320458</x22>
			<y22>431.753916</y22>
			<x23>439.130294</x23>
			<y23>428.688285</y23>
			<x24>438.478112</x24>
			<y24>425.188532</y24>
			<x25>439.998536</x25>
			<y25>423.764246</y25>
			<x26>458.231594</x26>
			<y26>320.359432</y26>
			<x27>459.752018</x27>
			<y27>318.935146</y27>
			<x28>458.810422</x28>
			<y28>317.07674</y28>
			<x29>471.255208</x29>
			<y29>246.498851</y29>
			<x30>470.240257</x30>
			<y30>237.857999</y30>
			<x31>466.003074</x31>
			<y31>229.49517</y31>
			<x32>460.13744</x32>
			<y32>226.768522</y32>
			<x33>399.817965</x33>
			<y33>216.132572</y33>
			<x34>400.86759</x34>
			<y34>213.779082</y34>
			<x35>399.455196</x35>
			<y35>210.991473</y35>
			<x36>395.943551</x36>
			<y36>212.910842</y36>
			<x37>396.124936</x37>
			<y37>215.48139</y37>
			<x38>389.969887</x38>
			<y38>214.396089</y38>
			<x39>391.019512</x39>
			<y39>212.0426</y39>
			<x40>389.607119</x40>
			<y40>209.25499</y40>
			<x41>386.095473</x41>
			<y41>211.174359</y41>
			<x42>386.276858</x42>
			<y42>213.744909</y42>
			<x43>380.121809</x43>
			<y43>212.659608</y43>
			<x44>381.171435</x44>
			<y44>210.306119</y44>
			<x45>379.75904</x45>
			<y45>207.518509</y45>
			<x46>376.247396</x46>
			<y46>209.437878</y46>
			<x47>377.65979</x47>
			<y47>212.225488</y47>
			<x48>370.273732</x48>
			<y48>210.923126</y48>
			<x49>369.910963</x49>
			<y49>205.782028</y49>
			<x50>366.399319</x50>
			<y50>207.701396</y50>
			<x51>367.811713</x51>
			<y51>210.489006</y51>
			<x52>360.425654</x52>
			<y52>209.186644</y52>
			<x53>360.062886</x53>
			<y53>204.045545</y53>
			<x54>356.551241</x54>
			<y54>205.964914</y54>
			<x55>356.732626</x55>
			<y55>208.535464</y55>
			<x56>350.577577</x56>
			<y56>207.450162</y56>
			<x57>350.214808</x57>
			<y57>202.309064</y57>
			<x58>343.010134</x58>
			<y58>203.577251</y58>
			<x59>347.173962</x59>
			<y59>205.157635</y59>
			<x60>346.884548</x60>
			<y60>206.798982</y60>
			<x61>340.7295</x61>
			<y61>205.713681</y61>
			<x62>341.779125</x62>
			<y62>203.360191</y62>
			<x63>340.366731</x63>
			<y63>200.572582</y63>
			<x64>337.615298</x64>
			<y64>201.779808</y64>
			<x65>329.287644</x65>
			<y65>198.61904</y65>
			<x66>327.188393</x66>
			<y66>203.326018</y66>
			<x67>321.033344</x67>
			<y67>202.240717</y67>
			<x68>320.670575</x68>
			<y68>197.099618</y68>
			<x69>318.679354</x69>
			<y69>197.5947</y69>
			<x70>317.340315</x70>
			<y70>201.589537</y70>
			<x71>311.185267</x71>
			<y71>200.504236</y71>
			<x72>310.822498</x72>
			<y72>195.363137</y72>
			<x73>307.310854</x73>
			<y73>197.282506</y73>
			<x74>307.492238</x74>
			<y74>199.853054</y74>
			<x75>301.337189</x75>
			<y75>198.767753</y75>
			<x76>300.974421</x76>
			<y76>193.626654</y76>
			<x77>298.9832</x77>
			<y77>194.121737</y77>
			<x78>297.644161</x78>
			<y78>198.116573</y78>
			<x79>291.489112</x79>
			<y79>197.031272</y79>
			<x80>290.836929</x80>
			<y80>193.53152</y80>
			<x81>287.796082</x81>
			<y81>196.380092</y81>
			<x82>285.91289</x82>
			<y82>192.663279</y82>
			<x83>282.872044</x83>
			<y83>195.51185</y83>
			<x84>280.988852</x84>
			<y84>191.795037</y84>
			<x85>277.948005</x85>
			<y85>194.643609</y85>
			<x86>271.792956</x86>
			<y86>193.558308</y86>
			<x87>271.140774</x87>
			<y87>190.058556</y87>
			<x88>266.868918</x88>
			<y88>192.690068</y88>
			<x89>264.985726</x89>
			<y89>188.973255</y89>
			<x90>261.944879</x90>
			<y90>191.821826</y90>
			<x91>260.3511</x91>
			<y91>186.463668</y91>
			<x92>258.25185</x92>
			<y92>191.170646</y92>
			<x93>256.368658</x93>
			<y93>187.453833</y93>
			<x94>253.327811</x94>
			<y94>190.302405</y94>
			<x95>251.444619</x95>
			<y95>186.585592</y95>
			<x96>248.403773</x96>
			<y96>189.434164</y96>
			<x97>245.289571</x97>
			<y97>185.500291</y97>
			<x98>242.248724</x98>
			<y98>188.348863</y98>
			<x99>241.885956</x99>
			<y99>183.207764</y99>
			<x100>239.894734</x100>
			<y100>183.702847</y100>
			<x101>238.555695</x101>
			<y101>187.697682</y101>
			<x102>236.672502</x102>
			<y102>183.98087</y102>
			<x103>233.92107</x103>
			<y103>185.188095</y103>
			<x104>232.037878</x104>
			<y104>181.471282</y104>
			<x105>227.476608</x105>
			<y105>185.74414</y105>
			<x106>227.11384</x106>
			<y106>180.603041</y106>
			<x107>224.362406</x107>
			<y107>181.810267</y107>
			<x108>222.1898</x108>
			<y108>179.734801</y108>
			<x109>219.438368</x109>
			<y109>180.942027</y109>
			<x110>217.265761</x110>
			<y110>178.86656</y110>
			<x111>214.514328</x111>
			<y111>180.073786</y111>
			<x112>213.572732</x112>
			<y112>178.215379</y112>
			<x113>209.590289</x113>
			<y113>179.205544</y113>
			<x114>207.417684</x114>
			<y114>177.130078</y114>
			<x115>204.666251</x115>
			<y115>178.337304</y115>
			<x116>203.724655</x116>
			<y116>176.478897</y116>
			<x117>198.511202</x117>
			<y117>177.252003</y117>
			<x118>197.569606</x118>
			<y118>175.393596</y118>
			<x119>194.818173</x119>
			<y119>176.600822</y119>
			<x120>193.876578</x120>
			<y120>174.742416</y120>
			<x121>188.663125</x121>
			<y121>175.515521</y121>
			<x122>187.721529</x122>
			<y122>173.657114</y122>
			<x123>184.970096</x123>
			<y123>174.86434</y123>
			<x124>181.566481</x124>
			<y124>172.571813</y124>
			<x125>179.285845</x125>
			<y125>174.708242</y125>
			<x126>180.227442</x126>
			<y126>176.566649</y126>
			<x127>178.23622</x127>
			<y127>177.061732</y127>
			<x128>178.34425</x128>
			<y128>172.849835</y128>
			<x129>176.642442</x129>
			<y129>171.703572</y129>
			<x130>175.303403</x130>
			<y130>175.698408</y130>
			<x131>173.312182</x131>
			<y131>176.193491</y131>
			<x132>173.238826</x132>
			<y132>169.411045</y132>
			<x133>169.619152</x133>
			<y133>175.54231</y133>
			<x134>148.691987</x134>
			<y134>171.852286</y134>
			<x135>148.800016</x135>
			<y135>167.64039</y135>
			<x136>147.098209</x136>
			<y136>166.494127</y136>
			<x137>144.998959</x137>
			<y137>171.201105</y137>
			<x138>138.84391</x138>
			<y138>170.115804</y138>
			<x139>138.191728</x139>
			<y139>166.616052</y139>
			<x140>135.150881</x140>
			<y140>169.464624</y140>
			<x141>128.995833</x141>
			<y141>168.379323</y141>
			<x142>127.112641</x142>
			<y142>164.66251</y142>
			<x143>125.302804</x143>
			<y143>167.728142</y143>
			<x144>116.396322</x144>
			<y144>167.850067</y144>
			<x145>109.265003</x145>
			<y145>175.9007</y145>
			<x146>104.055558</x146>
			<y146>205.444932</y146>
			<x147>102.535135</x147>
			<y147>206.869219</y147>
			<x148>102.897903</x148>
			<y148>212.010318</y148>
			<x149>101.37748</x149>
			<y149>213.434603</y149>
			<x150>94.431553</x150>
			<y150>252.826914</y150>
			<x151>92.91113</x151>
			<y151>254.2512</y151>
			<x152>93.852725</x152>
			<y152>256.109606</y152>
			<x153>92.042889</x153>
			<y153>259.175238</y153>
			<x154>92.984485</x154>
			<y154>261.033645</y154>
			<x155>90.885234</x155>
			<y155>265.740624</y155>
			<x156>91.537417</x156>
			<y156>269.240376</y156>
			<x157>89.727579</x157>
			<y157>272.306009</y157>
			<x158>90.669176</x158>
			<y158>274.164414</y158>
			<x159>87.122857</x159>
			<y159>287.078126</y159>
			<x160>88.064453</x160>
			<y160>288.93653</y160>
			<x161>86.54403</x161>
			<y161>290.360817</y161>
			<x162>56.553042</x162>
			<y162>456.848932</y162>
			<x163>58.220176</x163>
			<y163>468.989537</y163>
			<x164>68.431022</x164>
			<y164>475.867117</y164>
			<x165>144.753623</x165>
			<y165>489.324851</y165>
			<x166>145.695218</x166>
			<y166>491.183257</y166>
			<x167>148.446651</x167>
			<y167>489.976031</y167>
			<x168>150.619258</x168>
			<y168>492.051498</y168>
			<x169>152.139681</x169>
			<y169>490.627213</y169>
			<x170>155.543297</x170>
			<y170>492.91974</y170>
			<x171>158.294729</x171>
			<y171>491.712513</y171>
			<x172>161.698344</x172>
			<y172>494.005041</y172>
			<x173>163.218768</x173>
			<y173>492.580754</y173>
			<x174>164.160364</x174>
			<y174>494.439161</y174>
			<x175>171.546422</x175>
			<y175>495.741522</y175>
			<x176>173.066846</x176>
			<y176>494.317236</y176>
			<x177>243.234398</x177>
			<y177>506.689669</y177>
			<x178>244.175994</x178>
			<y178>508.548076</y178>
			<x179>254.024071</x179>
			<y179>510.284557</y179>
			<x180>255.544495</x180>
			<y180>508.860271</y180>
			<x181>400.803639</x181>
			<y181>534.473377</y181>
			<x182>413.981976</x182>
			<y182>531.71994</y182>
			<x183>422.923132</x183>
			<y183>520.603675</y183>
			<x184>421.981535</x184>
			<y184>518.745269</y184>
		</polygon>
	</object>
</annotation>
